MANIFEST.in
README.md
setup.cfg
setup.py
seestar/AngleDisks.py
seestar/ArrayMechanics.py
seestar/ComputerOps.py
seestar/CoordTrans.py
seestar/DataImport.py
seestar/DistributionPlots.py
seestar/FieldAssignment.py
seestar/FieldUnions.py
seestar/IsochroneScaling.py
seestar/Optimizers.py
seestar/PlotCoordinates.py
seestar/SFInstanceClasses.py
seestar/SelectionGrid.py
seestar/StatisticalModels.py
seestar/__init__.py
seestar/createNew.py
seestar/surveyInfoPickler.py
seestar.egg-info/PKG-INFO
seestar.egg-info/SOURCES.txt
seestar.egg-info/dependency_links.txt
seestar.egg-info/requires.txt
seestar.egg-info/top_level.txt