Metadata-Version: 1.1
Name: seestar
Version: 1.0
Summary: Selection Function package
Home-page: https://github.aeverall/seestar.git
Author: Andrew Everall
Author-email: andrew.everall1995@gmail.com
License: GPLv3
Platform: UNKNOWN
Classifier: Topic :: Scientific/Engineering :: Astronomy
Classifier: Intended Audience :: Science/Research
Classifier: License :: OSI Approved :: GNU General Public License v3 (GPLv3)
Classifier: Natural Language :: English
Classifier: Programming Language :: Python :: 2.7
Classifier: Programming Language :: Python :: 2 :: Only
Classifier: Programming Language :: Python :: 3 :: Only
Classifier: Programming Language :: Python :: 3.5
